hubs_predictor/__init__.py
hubs_predictor-0.1.2.dist-info/METADATA
hubs_predictor-0.1.2.dist-info/WHEEL
hubs_predictor-0.1.2.dist-info/top_level.txt
hubs_predictor-0.1.2.dist-info/RECORD
