Metadata-Version: 2.1
Name: hubs-predictor
Version: 0.1.2
Summary: Price predictions for 3DHubs
Home-page: https://github.com/3DHubs/ml-engineer-assignment-bendangnuksung/
Author: bendangnuksung
Author-email: bendangnuksungimsong@gmail.com
License: UNKNOWN
Platform: UNKNOWN
Classifier: Programming Language :: Python :: 3
Classifier: Operating System :: OS Independent
Requires-Dist: pandas (>=1.3.5)
Requires-Dist: numpy
Requires-Dist: requests
